Metadata-Version: 2.1
Name: Seq2Neo
Version: 2.1.1
Summary: Seq2Neo: a comprehensive pipeline for cancer neoantigen immunogenicity prediction
Home-page: https://github.com/XSLiuLab/Seq2Neo
Author: Kaixuan Diao
Author-email: diaokx@shanghaitech.edu.cn
License: UNKNOWN
Keywords: neoantigen fusion immunogenicity prediction sequencing cancer
Platform: UNKNOWN
Classifier: Programming Language :: Python :: 3.7
Classifier: License :: OSI Approved :: Academic Free License (AFL)
Classifier: Operating System :: POSIX :: Linux
Classifier: Topic :: Scientific/Engineering :: Bio-Informatics
Requires-Python: >=3
License-File: LICENSE
Requires-Dist: protobuf (<3.20)
Requires-Dist: biopython (==1.77)
Requires-Dist: keras (==2.4.3)
Requires-Dist: tensorflow (==2.3.0)
Requires-Dist: agfusion (==1.252)
